inetlab/__init__.py
inetlab/auth/__init__.py
inetlab/auth/synauth.py
inetlab/auth/synlogin.py
inetlab/cli/__init__.py
inetlab/cli/colorterm.py
inetlab/cli/config.py
inetlab/cli/genformatter.py
inetlab/cli/inputnums.py
inetlab/gae/__init__.py
inetlab/gae/dbgyamlenv.py
inetlab/gae/gaedbconn.py
inetlab/html/__init__.py
inetlab/html/html2xml.py
inetlab/html/htmladdons.py
inetlab/html/htmlbuilder.py
inetlab/html/inputlib.py
inetlab/html/jsescape.py
inetlab/mail/__init__.py
inetlab/mail/gmail_api.py
inetlab/mail/xmail.py
inetlab/sql/__init__.py
inetlab/sql/sqldbconn.py
inetlab/utils/__init__.py
inetlab/utils/csv.py
inetlab/utils/mylangutils.py
inetlab/utils/stringsdist.py
inetlab/utils/xmlobj.py
inetlab/web/__init__.py
inetlab/web/urlutils.py
inetlab-0.1.9.dist-info/LICENSE
inetlab-0.1.9.dist-info/METADATA
inetlab-0.1.9.dist-info/WHEEL
inetlab-0.1.9.dist-info/entry_points.txt
inetlab-0.1.9.dist-info/top_level.txt
inetlab-0.1.9.dist-info/RECORD
