Metadata-Version: 2.1
Name: inetlab
Version: 0.1.9
Summary: Python helper libraries for Web/GAE/Flask, HTML manipulation and command line tools
Home-page: https://github.com/kign/pkg-inetlab
Author: Konstantin Ignatiev
Author-email: kostya@inet-lab.net
Project-URL: Bug Tracker, https://github.com/kign/pkg-inetlab/issues
Classifier: Programming Language :: Python :: 3
Classifier: License :: OSI Approved :: GNU General Public License v2 (GPLv2)
Classifier: Operating System :: OS Independent
Requires-Python: >=3.7
License-File: LICENSE
